peewee_redshift/__init__.py
peewee_redshift-0.0.1.dist-info/LICENSE
peewee_redshift-0.0.1.dist-info/METADATA
peewee_redshift-0.0.1.dist-info/WHEEL
peewee_redshift-0.0.1.dist-info/top_level.txt
peewee_redshift-0.0.1.dist-info/RECORD
