Metadata-Version: 2.1
Name: peewee-redshift
Version: 0.0.1
Summary: An Amazon Redshift database extension for the Pewee ORM
Home-page: UNKNOWN
Author: Christopher Boyd
License: UNKNOWN
Platform: UNKNOWN
Classifier: Programming Language :: Python :: 3
Classifier: License :: OSI Approved :: MIT License
Classifier: Operating System :: OS Independent
Requires-Python: >=3.6
Requires-Dist: peewee
